{
  "id": "user-management-service-development-environment-id",
  "name": "User Management Service - Development",
  "values": [
    {
      "key": "baseUrl",
      "value": "http://user-management.dev.local/api/v1",
      "type": "default",
      "enabled": true,
      "description": "Base URL for development environment"
    },
    {
      "key": "testUsername",
      "value": "dev-test-user",
      "type": "default",
      "enabled": true,
      "description": "Development test username"
    },
    {
      "key": "testEmail",
      "value": "dev-test-user@dev.local",
      "type": "default",
      "enabled": true,
      "description": "Development test email address"
    },
    {
      "key": "testFullName",
      "value": "Development Test User",
      "type": "default",
      "enabled": true,
      "description": "Development test user's full name"
    },
    {
      "key": "testPassword",
      "value": "REPLACE_WITH_YOUR_TEST_USER_PASSWORD",
      "type": "secret",
      "enabled": true,
      "description": "Development test user password (replace with actual)"
    },
    {
      "key": "adminUsername",
      "value": "dev-admin-user",
      "type": "default",
      "enabled": true,
      "description": "Development admin username"
    },
    {
      "key": "adminEmail",
      "value": "dev-admin@dev.local",
      "type": "default",
      "enabled": true,
      "description": "Development admin email address"
    },
    {
      "key": "adminPassword",
      "value": "REPLACE_WITH_YOUR_ADMIN_USER_PASSWORD",
      "type": "secret",
      "enabled": true,
      "description": "Development admin password (replace with actual)"
    },
    {
      "key": "accessToken",
      "value": "",
      "type": "secret",
      "enabled": true,
      "description": "OAuth2 Bearer token for authenticated requests"
    },
    {
      "key": "adminAccessToken",
      "value": "",
      "type": "secret",
      "enabled": true,
      "description": "Admin OAuth2 Bearer token for administrative requests"
    },
    {
      "key": "userId",
      "value": "",
      "type": "default",
      "enabled": true,
      "description": "Current authenticated user's ID"
    },
    {
      "key": "targetUserId",
      "value": "",
      "type": "default",
      "enabled": true,
      "description": "Target user ID for operations on other users (set to actual dev user ID)"
    },
    {
      "key": "notificationId",
      "value": "",
      "type": "default",
      "enabled": true,
      "description": "Sample notification ID for testing (set to actual dev notification ID)"
    },
    {
      "key": "notificationId1",
      "value": "",
      "type": "default",
      "enabled": true,
      "description": "First notification ID for bulk operations (set to actual ID)"
    },
    {
      "key": "notificationId2",
      "value": "",
      "type": "default",
      "enabled": true,
      "description": "Second notification ID for bulk operations (set to actual ID)"
    },
    {
      "key": "deletionToken",
      "value": "",
      "type": "secret",
      "enabled": true,
      "description": "Account deletion confirmation token"
    }
  ]
}
